sprite/server.py
sprite/lib/sprite_server.py
sprite/lib/util/constants.py
sprite/lib/util/utils.py
sprite/static/common/bootstrap.min.css
sprite/static/common/bootstrap.min.js
sprite/static/common/jquery.min.js
sprite/static/common/string-format.min.js
sprite/static/image/favicon.ico
sprite/static/image/file.png
sprite/static/image/folder.png
sprite/static/image/upper.png
sprite/template/common.html
sprite/template/error.html
sprite/template/list.html
sprite_server-1.0.3.dist-info/licenses/LICENSE
sprite_server-1.0.3.dist-info/METADATA
sprite_server-1.0.3.dist-info/WHEEL
sprite_server-1.0.3.dist-info/top_level.txt
sprite_server-1.0.3.dist-info/RECORD
